mpsmarthome/__init__.py
mpsmarthome/api_client.py
mpsmarthome/api_response.py
mpsmarthome/configuration.py
mpsmarthome/exceptions.py
mpsmarthome/py.typed
mpsmarthome/rest.py
mpsmarthome/api/__init__.py
mpsmarthome/api/home_assistant_api.py
mpsmarthome/api/homey_api.py
mpsmarthome/models/__init__.py
mpsmarthome/models/auth_request.py
mpsmarthome/models/auth_response.py
mpsmarthome/models/full_request.py
mpsmarthome/models/meter_reading_data.py
mpsmarthome/models/meter_reading_response.py
mpsmarthome/models/meter_reading_response_data.py
mpsmarthome/models/meters_response.py
mpsmarthome/models/partial_request.py
mpsmarthome-1.0.2.dist-info/METADATA
mpsmarthome-1.0.2.dist-info/WHEEL
mpsmarthome-1.0.2.dist-info/top_level.txt
mpsmarthome-1.0.2.dist-info/RECORD
