Metadata-Version: 2.1
Name: mpsmarthome
Version: 1.0.2
Summary: SmartHome
Home-page: 
Author: OpenAPI Generator community
Author-email: team@openapitools.org
Keywords: OpenAPI,OpenAPI-Generator,SmartHome
Requires-Dist: urllib3 <2.1.0,>=1.25.3
Requires-Dist: python-dateutil
Requires-Dist: aiohttp >=3.0.0
Requires-Dist: pydantic <2,>=1.10.5
Requires-Dist: aenum
